moccasin/__init__.py
moccasin/__main__.py
moccasin/_dependency_utils.py
moccasin/_sys_path_and_config_setup.py
moccasin/boa_tools.py
moccasin/config.py
moccasin/logging.py
moccasin/moccasin_account.py
moccasin/named_contract.py
moccasin/plugin.py
moccasin/supported_verifiers.py
moccasin/commands/__init__.py
moccasin/commands/compile.py
moccasin/commands/config_.py
moccasin/commands/console.py
moccasin/commands/deploy.py
moccasin/commands/deployments.py
moccasin/commands/explorer.py
moccasin/commands/format.py
moccasin/commands/init.py
moccasin/commands/inspect.py
moccasin/commands/install.py
moccasin/commands/lint.py
moccasin/commands/purge.py
moccasin/commands/run.py
moccasin/commands/test.py
moccasin/commands/utils.py
moccasin/commands/vyper.py
moccasin/commands/wallet.py
moccasin/constants/chains.py
moccasin/constants/file_data.py
moccasin/constants/vars.py
moccasin/data/metamask_ui/README.md
moccasin/data/metamask_ui/index.html
moccasin/data/metamask_ui/js/api.js
moccasin/data/metamask_ui/js/elements.js
moccasin/data/metamask_ui/js/main.js
moccasin/data/metamask_ui/js/metamask.js
moccasin/data/metamask_ui/js/polling.js
moccasin/data/metamask_ui/js/state.js
moccasin/data/metamask_ui/js/ui.js
moccasin/metamask_cli_integration/README.md
moccasin/metamask_cli_integration/__init__.py
moccasin/metamask_cli_integration/account.py
moccasin/metamask_cli_integration/constants.py
moccasin/metamask_cli_integration/http_handler.py
moccasin/metamask_cli_integration/server_control.py
moccasin/metamask_cli_integration/server_lifecycle.py
moccasin/metamask_cli_integration/utils.py
moccasin-0.4.3.dist-info/METADATA
moccasin-0.4.3.dist-info/WHEEL
moccasin-0.4.3.dist-info/entry_points.txt
moccasin-0.4.3.dist-info/RECORD
