Metadata-Version: 2.4
Name: moccasin
Version: 0.4.3
Summary: Pythonic smart contract development framework using Titanoboa
Project-URL: Repository, https://github.com/cyfrin/moccasin
Project-URL: Documentation, https://cyfrin.github.io/moccasin/
Project-URL: Releases, https://github.com/Cyfrin/moccasin/releases
Author-email: PatrickAlphac <54278053+PatrickAlphaC@users.noreply.github.com>, charles-cooper <3867501+charles-cooper@users.noreply.github.com>
Keywords: blockchain,ethereum,moccasin,mox,smart-contract,zksync
Classifier: Development Status :: 4 - Beta
Classifier: Environment :: Console
Classifier: Intended Audience :: Developers
Classifier: Operating System :: OS Independent
Classifier: Programming Language :: Python
Classifier: Programming Language :: Python :: 3 :: Only
Classifier: Programming Language :: Python :: 3.11
Classifier: Programming Language :: Python :: 3.12
Classifier: Programming Language :: Python :: 3.13
Classifier: Topic :: Software Development
Classifier: Topic :: Software Development :: Build Tools
Classifier: Topic :: Software Development :: Libraries
Classifier: Topic :: Software Development :: Quality Assurance
Classifier: Topic :: Software Development :: Testing
Classifier: Topic :: Utilities
Requires-Python: <=3.13,>=3.11
Requires-Dist: ipykernel>=6.29.5
Requires-Dist: pytest-cov>=5.0.0
Requires-Dist: pytest-xdist>=3.6.1
Requires-Dist: python-dotenv>=1.0.1
Requires-Dist: titanoboa-zksync>=0.2.10
Requires-Dist: titanoboa>=v0.2.6
Requires-Dist: tomli-w>=1.0.0
Requires-Dist: tomlkit>=0.13.2
Requires-Dist: tqdm>=4.66.5
Requires-Dist: uv>=0.4.15
Requires-Dist: vyper>=0.4.1
Provides-Extra: docs
Requires-Dist: shibuya>=2024.8.30; extra == 'docs'
Requires-Dist: sphinx-argparse>=0.5.2; extra == 'docs'
Requires-Dist: sphinx-copybutton>=0.5.2; extra == 'docs'
Requires-Dist: sphinx-multiversion>=0.2.4; extra == 'docs'
Requires-Dist: sphinx-tabs>=3.4.5; extra == 'docs'
Requires-Dist: sphinx>=8.0.2; extra == 'docs'
Requires-Dist: watchdog>=5.0.2; extra == 'docs'
